scpi/__init__.py
scpi/devices/TDKLambdaZPlus.py
scpi/devices/__init__.py
scpi/devices/generic.py
scpi/devices/hp6632b.py
scpi/errors/__init__.py
scpi/py.typed
scpi/scpi.py
scpi/transports/__init__.py
scpi/transports/baseclass.py
scpi/transports/gpib/__init__.py
scpi/transports/gpib/base.py
scpi/transports/gpib/prologix.py
scpi/transports/rs232.py
scpi/transports/tcp.py
scpi/wrapper.py
scpi-2.5.1.dist-info/LICENSE
scpi-2.5.1.dist-info/METADATA
scpi-2.5.1.dist-info/WHEEL
scpi-2.5.1.dist-info/RECORD
