Metadata-Version: 2.1
Name: scpi
Version: 2.5.1
Summary: Basic idea here is to make transport-independent command sender/parser and a device baseclass that implements the common SCPI commands
Home-page: https://github.com/rambo/python-scpi/
License: LGPL
Author: Eero af Heurlin
Author-email: eero.afheurlin@iki.fi
Requires-Python: >=3.9,<4.0
Classifier: License :: Other/Proprietary License
Classifier: Programming Language :: Python :: 3
Classifier: Programming Language :: Python :: 3.9
Classifier: Programming Language :: Python :: 3.10
Classifier: Programming Language :: Python :: 3.11
Classifier: Programming Language :: Python :: 3.12
Classifier: Programming Language :: Python :: 3.13
Requires-Dist: pyserial (>=3.4,<4.0)
Project-URL: Repository, https://github.com/rambo/python-scpi/
